poodle/__init__.py
poodle/client.py
poodle/exceptions.py
poodle/version.py
poodle_python-0.1.1.dist-info/LICENSE
poodle_python-0.1.1.dist-info/METADATA
poodle_python-0.1.1.dist-info/WHEEL
poodle_python-0.1.1.dist-info/RECORD
