Metadata-Version: 2.3
Name: poodle-python
Version: 0.1.1
Summary: Python SDK for the Poodle's email sending API
License: MIT
Author: Wilbert Liu
Author-email: wilbert@usepoodle.com
Requires-Python: >=3.9,<4.0
Classifier: Development Status :: 4 - Beta
Classifier: Intended Audience :: Developers
Classifier: License :: OSI Approved :: MIT License
Classifier: Operating System :: OS Independent
Classifier: Programming Language :: Python :: 3
Classifier: Programming Language :: Python :: 3.9
Classifier: Programming Language :: Python :: 3.10
Classifier: Programming Language :: Python :: 3.11
Classifier: Programming Language :: Python :: 3.12
Classifier: Programming Language :: Python :: 3.13
Classifier: Topic :: Communications :: Email
Classifier: Topic :: Software Development :: Libraries :: Python Modules
Requires-Dist: requests (>=2.31.0,<3.0.0)
Project-URL: Documentation, https://github.com/usepoodle/poodle-python
Project-URL: Homepage, https://usepoodle.com
Project-URL: Repository, https://github.com/usepoodle/poodle-python
